[
  {
    "name": "Toxicity",
    "image": "https://i.scdn.co/image/ab67616d0000b27330d45198d0c9e8841f9a9578",
    "link": "https://open.spotify.com/album/6jWde94ln40epKIQCd8XUh",
    "artists": [
      {
        "name": "System Of A Down",
        "link": "https://open.spotify.com/artist/5eAWCfyUhZtHHtBdNk56l1"
      }
    ],
    "rating": 6.5,
    "recommended by": "Victor",
    "best songs": [
      "Prison Song",
      "Science"
    ],
    "comment": "Paar goeie maar af en toe te veel"
  },
  {
    "name": "The Fat of the Land",
    "image": "https://i.scdn.co/image/ab67616d0000b2738688e410538bc27972791f4c",
    "link": "https://open.spotify.com/album/4fdgcEVMdJe0KVgupMNJAP",
    "artists": [
      {
        "name": "The Prodigy",
        "link": "https://open.spotify.com/artist/4k1ELeJKT1ISyDv8JivPpB"
      }
    ],
    "rating": 6.5,
    "recommended by": "Kasper",
    "best songs": [
      "Diesel Power",
      "Firestarter"
    ],
    "comment": "Leuke nummers maar vocals zijn wat minder"
  },
  {
    "name": "The Velvet Underground & Nico 45th Anniversary",
    "image": "https://i.scdn.co/image/ab67616d0000b27398260c528e6eec9dd431c1d7",
    "link": "https://open.spotify.com/album/4xwx0x7k6c5VuThz5qVqmV",
    "artists": [
      {
        "name": "The Velvet Underground",
        "link": "https://open.spotify.com/artist/1nJvji2KIlWSseXRSlNYsC"
      },
      {
        "name": "Nico",
        "link": "https://open.spotify.com/artist/0IwlY33zbBXN7zlS9DP2Cj"
      }
    ],
    "rating": 7.5,
    "recommended by": "Kasper",
    "best songs": [
      "Sunday Morning",
      "Run Run Run"
    ],
    "comment": "Goed tempo qua liedjes"
  },
  {
    "name": "In Rainbows",
    "image": "https://i.scdn.co/image/ab67616d0000b273de3c04b5fc750b68899b20a9",
    "link": "https://open.spotify.com/album/5vkqYmiPBYLaalcmjujWxK",
    "artists": [
      {
        "name": "Radiohead",
        "link": "https://open.spotify.com/artist/4Z8W4fKeB5YxbusRsdQVPb"
      }
    ],
    "rating": 9,
    "recommended by": "Veerle",
    "best songs": [
      "15 Step",
      "Bodysnatchers",
      "Nude",
      "Weird Fished/ Arpeggi",
      "House of Cards",
      "Jigsaw Falling Into Place",
      "Videotape"
    ],
    "comment": "Waarchijnlijk 9 omdat ik er al naar luister"
  },
  {
    "name": "Sic Fiction",
    "image": "https://i.scdn.co/image/ab67616d0000b2735691e025e887bd8d2826ae65",
    "link": "https://open.spotify.com/album/2qV6WbCRQvmhT1XA3GYqc1",
    "artists": [
      {
        "name": "Rochambeaux",
        "link": "https://open.spotify.com/artist/1ZzNc0QqXkZxFCb3Wq8QdD"
      }
    ],
    "rating": 8,
    "recommended by": "Victor",
    "best songs": [
      "Front Porch",
      "Stated in Context",
      "Sum of Hearts"
    ],
    "comment": "6 is actually insane"
  },
  {
    "name": "Lateralus",
    "image": "https://i.scdn.co/image/ab67616d0000b273ca41a947c13b78749c4953b1",
    "link": "https://open.spotify.com/album/5l5m1hnH4punS1GQXgEi3T",
    "artists": [
      {
        "name": "TOOL",
        "link": "https://open.spotify.com/artist/2yEwvVSSSUkcLeSTNyHKh8"
      }
    ],
    "rating": 8.5,
    "recommended by": "Kasper",
    "best songs": [
      "Lateralus",
      "Reflection"
    ],
    "comment": "I like m(e)ath"
  },
  {
    "name": "First Band On The Moon (Remastered)",
    "image": "https://i.scdn.co/image/ab67616d0000b2730aac8ca880151fda470e91af",
    "link": "https://open.spotify.com/album/56vFkneGivqQcoNQq362iZ",
    "artists": [
      {
        "name": "The Cardigans",
        "link": "https://open.spotify.com/artist/1tqZaCwM57UFKjWoYwMLrw"
      }
    ],
    "rating": 8,
    "recommended by": "Veerle",
    "best songs": [
      "Been It",
      "Lovefool"
    ],
    "comment": "Lovefool is een banger"
  },
  {
    "name": "BADLANDS (Deluxe)",
    "image": "https://i.scdn.co/image/ab67616d0000b27374fefed78db6d6cf4d963fdc",
    "link": "https://open.spotify.com/album/5OZJflQcQCdZLQjtUudCin",
    "artists": [
      {
        "name": "Halsey",
        "link": "https://open.spotify.com/artist/26VFTg2z8YR0cCuwLzESi2"
      }
    ],
    "rating": 8.5,
    "recommended by": "Victor",
    "best songs": [
      "Castle",
      "New Americana",
      "Roman Holiday",
      "Strange Love",
      "Gasoline",
      "Young God"
    ],
    "comment": "Literally just pop"
  },
  {
    "name": "Siamese Dream (Deluxe Edition)",
    "image": "https://i.scdn.co/image/ab67616d0000b2735274788f34fc7656d2856dfd",
    "link": "https://open.spotify.com/album/0bQglEvsHphrS19FGODEGo",
    "artists": [
      {
        "name": "The Smashing Pumpkins",
        "link": "https://open.spotify.com/artist/40Yq4vzPs9VNUrIBG5Jr2i"
      }
    ],
    "rating": 8,
    "recommended by": "Kasper",
    "best songs": [
      "Today",
      "Disarm"
    ],
    "comment": "Er zit niet heel veel range op het volume"
  },
  {
    "name": "How To Be A Human Being",
    "image": "https://i.scdn.co/image/ab67616d0000b273ec3d15eab5bd77027abc4b23",
    "link": "https://open.spotify.com/album/6qb9MDR0lfsN9a2pw77uJy",
    "artists": [
      {
        "name": "Glass Animals",
        "link": "https://open.spotify.com/artist/4yvcSjfu4PC0CYQyLy4wSq"
      }
    ],
    "rating": 9,
    "recommended by": "Veerle",
    "best songs": [
      "Life Itself",
      "Youth",
      "Season 2 Episode 3"
    ],
    "comment": "Gewoon goede nummers"
  },
  {
    "name": "O My Heart",
    "image": "https://i.scdn.co/image/ab67616d0000b273bf77ec4fe60aa3163d91e767",
    "link": "https://open.spotify.com/album/41U6Qbx5KxhHYIuwlK3lXA",
    "artists": [
      {
        "name": "Mother Mother",
        "link": "https://open.spotify.com/artist/0e86yPdC41PGRkLp2Q1Bph"
      }
    ],
    "rating": 9,
    "recommended by": "Victor",
    "best songs": [
      "O My Heart",
      "Burning Pile",
      "Wisdom",
      "Body",
      "Hayloft"
    ],
    "comment": "Makkelijk in te komen"
  },
  {
    "name": "Plastic Beach",
    "image": "https://i.scdn.co/image/ab67616d0000b273661d019f34569f79eae9e985",
    "link": "https://open.spotify.com/album/2dIGnmEIy1WZIcZCFSj6i8",
    "artists": [
      {
        "name": "Gorillaz",
        "link": "https://open.spotify.com/artist/3AA28KZvwAUcZuOKwyblJQ"
      }
    ],
    "rating": 7.5,
    "recommended by": "Kasper",
    "best songs": [
      "Superfast Jellyfish",
      "On Melancholy Hill"
    ],
    "comment": "Ze hebben wel heel veel featuring"
  },
  {
    "name": "Mezzanine",
    "image": "https://i.scdn.co/image/ab67616d0000b2732fcb0a3c7a66e516b11cd26e",
    "link": "https://open.spotify.com/album/49MNmJhZQewjt06rpwp6QR",
    "artists": [
      {
        "name": "Massive Attack",
        "link": "https://open.spotify.com/artist/6FXMGgJwohJLUSr5nVlf9X"
      }
    ],
    "rating": 8,
    "recommended by": "Veerle",
    "best songs": [
      "Teardrop",
      "Exchange",
      "Dissolved Girl",
      "Man Next Door"
    ],
    "comment": "Allemaal goede liedjes"
  },
  {
    "name": "The Bastards",
    "image": "https://i.scdn.co/image/ab67616d0000b27369ec580ab2b0047ca579c766",
    "link": "https://open.spotify.com/album/5b2m10WqNvZaD8eTEXGyfl",
    "artists": [
      {
        "name": "Palaye Royale",
        "link": "https://open.spotify.com/artist/0hAd6zwEgt9ILuMDY1prcI"
      }
    ],
    "rating": 8,
    "recommended by": "Victor",
    "best songs": [
      "Little Bastards",
      "Tonight Is The Night I Die",
      "Lonely",
      "Hang on to Yourself"
    ],
    "comment": "Heel goed maar niet fantastisch"
  },
  {
    "name": "Doolittle",
    "image": "https://i.scdn.co/image/ab67616d0000b2730ab3c2a306c614fae36ff1d6",
    "link": "https://open.spotify.com/album/0DQyTVcDhK9wm0f6RaErWO",
    "artists": [
      {
        "name": "Pixies",
        "link": "https://open.spotify.com/artist/6zvul52xwTWzilBZl6BUbT"
      }
    ],
    "rating": 8.5,
    "recommended by": "Kasper",
    "best songs": [
      "Debaser",
      "Here Comes Your Man",
      "Monkey Gone to Heaven",
      "Mr. Grieves",
      "Hey"
    ],
    "comment": "Goede muziek sommige vocals vind ik een beetje ofputting"
  },
  {
    "name": "Mellon Collie And The Infinite Sadness (Remastered)",
    "image": "https://i.scdn.co/image/ab67616d0000b2734c42e40240028664f939f81c",
    "link": "https://open.spotify.com/album/4bPT6Q8ppaSNppk1kbEbLl",
    "artists": [
      {
        "name": "The Smashing Pumpkins",
        "link": "https://open.spotify.com/artist/40Yq4vzPs9VNUrIBG5Jr2i"
      }
    ],
    "rating": 8,
    "recommended by": "Veerle",
    "best songs": [
      "Tonight, Tonight",
      "Zero",
      "Bullet With Butterfly Wings",
      "1979",
      "By Starlight"
    ],
    "comment": "Hoe vaker je het luistert, hoe beter het is"
  },
  {
    "name": "Elmer stuff",
    "image": "https://mosaic.scdn.co/640/ab67616d00001e022f21d7055814236b28342b19ab67616d00001e026c56da9b33cc328696902abeab67616d00001e02e1f8df409a18d3e0fa70e051ab67616d00001e02eb7df03e6831fc84f60fa7b6",
    "link": "https://open.spotify.com/playlist/5cnoo00Jfq9lf3qtlq3Ygl",
    "artists": [
      {
        "name": "Elmer",
        "link": "https://open.spotify.com/artist/1ESdlHhFi2Ww9jt8qLOyYp"
      }
    ],
    "rating": 8.5,
    "recommended by": "Victor",
    "best songs": [
      "Nothing Ontploffing",
      "Ik Weiger",
      "Politiek Statement",
      "Je Vader",
      "Sorry"
    ],
    "comment": "Ik neuk je vader zonder condoom yeah"
  },
  {
    "name": "Madvillainy",
    "image": "https://i.scdn.co/image/ab67616d0000b27374dc897ea75402db37ef239a",
    "link": "https://open.spotify.com/album/19bQiwEKhXUBJWY6oV3KZk",
    "artists": [
      {
        "name": "Madvillain",
        "link": "https://open.spotify.com/artist/2aoFQUeHD1U7pL098lRsDU"
      },
      {
        "name": "Madlib",
        "link": "https://open.spotify.com/artist/5LhTec3c7dcqBvpLRWbMcf"
      },
      {
        "name": "MF DOOM",
        "link": "https://open.spotify.com/artist/2pAWfrd7WFF3XhVt9GooDL"
      }
    ],
    "rating": 7,
    "recommended by": "Kasper",
    "best songs": [
      "Strange Ways",
      "All Caps"
    ],
    "comment": "Het is goed maar ik voel hem niet helemaal"
  },
  {
    "name": "Dummy",
    "image": "https://i.scdn.co/image/ab67616d0000b273dc20397b139223620af148f6",
    "link": "https://open.spotify.com/album/3539EbNgIdEDGBKkUf4wno",
    "artists": [
      {
        "name": "Portishead",
        "link": "https://open.spotify.com/artist/6liAMWkVf5LH7YR9yfFy1Y"
      }
    ],
    "rating": 8.5,
    "recommended by": "Veerle",
    "best songs": [
      "Mysterons",
      "Strangers",
      "Wandering Star"
    ],
    "comment": "-"
  },
  {
    "name": "Avenged Sevenfold",
    "image": "https://i.scdn.co/image/ab67616d0000b27333c52ca8309741c6999ca742",
    "link": "https://open.spotify.com/album/3Id3VUk9jSKBD1guNo1buF",
    "artists": [
      {
        "name": "Avenged Sevenfold",
        "link": "https://open.spotify.com/artist/0nmQIMXWTXfhgOBdNzhGOs"
      }
    ],
    "rating": "-",
    "recommended by": "Victor",
    "best songs": [],
    "comment": "-"
  }
]